gllm_privacy.cpython-312-darwin.so
gllm_privacy.pyi
gllm_privacy/__init__.pyi
gllm_privacy/pii_detector/__init__.pyi
gllm_privacy/pii_detector/analyzer.pyi
gllm_privacy/pii_detector/anonymizer.pyi
gllm_privacy/pii_detector/constants.pyi
gllm_privacy/pii_detector/custom_lemma_context_aware_enhancer.pyi
gllm_privacy/pii_detector/text_analyzer.pyi
gllm_privacy/pii_detector/text_anonymizer.pyi
gllm_privacy/pii_detector/recognizer/__init__.pyi
gllm_privacy/pii_detector/recognizer/bank_account_number_recognizer.pyi
gllm_privacy/pii_detector/recognizer/bpjs_number_recognizer.pyi
gllm_privacy/pii_detector/recognizer/config.pyi
gllm_privacy/pii_detector/recognizer/credit_card_recognizer.pyi
gllm_privacy/pii_detector/recognizer/facebook_account_recognizer.pyi
gllm_privacy/pii_detector/recognizer/family_card_number_recognizer.pyi
gllm_privacy/pii_detector/recognizer/flair_recognizer.pyi
gllm_privacy/pii_detector/recognizer/gdplabs_employee_id_recognizer.pyi
gllm_privacy/pii_detector/recognizer/gdplabs_ner_api_remote_recognizer.pyi
gllm_privacy/pii_detector/recognizer/indonesian_phone_number_recognizer.pyi
gllm_privacy/pii_detector/recognizer/ktp_recognizer.pyi
gllm_privacy/pii_detector/recognizer/linkedin_account_recognizer.pyi
gllm_privacy/pii_detector/recognizer/money_recognizer.pyi
gllm_privacy/pii_detector/recognizer/npwp_recognizer.pyi
gllm_privacy/pii_detector/recognizer/organization_name_recognizer.pyi
gllm_privacy/pii_detector/recognizer/project_name_recognizer.pyi
gllm_privacy/pii_detector/recognizer/prosa_remote_recognizer.pyi
gllm_privacy/pii_detector/recognizer/transformers_recognizer.pyi
gllm_privacy/pii_detector/utils/__init__.pyi
gllm_privacy/pii_detector/utils/deanonymizer_mapping.pyi
gllm_privacy/pii_detector/utils/pseudo_anonymizer_mapping.pyi
gllm_privacy/pii_detector/utils/spacy_model_loader.pyi
gllm_privacy/pii_detector/utils/text_chunker.pyi
gllm_privacy/pii_detector/utils/faker_provider/__init__.pyi
gllm_privacy_binary-0.4.12.dist-info/METADATA
gllm_privacy_binary-0.4.12.dist-info/WHEEL
gllm_privacy_binary-0.4.12.dist-info/top_level.txt
gllm_privacy_binary-0.4.12.dist-info/RECORD
