Metadata-Version: 2.2
Name: gllm-privacy-binary
Version: 0.4.12
Author-email: GenAI SDK Team <gat-sdk@gdplabs.id>
Requires-Python: <3.14,>=3.11
Requires-Dist: gllm-core-binary<0.4.0,>=0.3.31
Requires-Dist: faker<31.0.0,>=30.3.0
Requires-Dist: numpy<2.0,>=1.26; python_version < "3.12"
Requires-Dist: numpy<2.0,>=1.26; python_version >= "3.12" and python_version < "3.13"
Requires-Dist: numpy<3.0,>=2.2; python_version >= "3.13"
Requires-Dist: presidio-analyzer<3.0.0,>=2.2.0
Requires-Dist: presidio_anonymizer<3.0.0,>=2.2.0
Requires-Dist: requests-mock<2.0.0,>=1.12.1
Requires-Dist: semver<4.0.0,>=3.0.4
Provides-Extra: dev
Requires-Dist: coverage<8.0.0,>=7.4.4; extra == "dev"
Requires-Dist: mypy<2.0.0,>=1.15.0; extra == "dev"
Requires-Dist: pre-commit<4.0.0,>=3.7.0; extra == "dev"
Requires-Dist: presidio-analyzer[transformers]<3.0.0,>=2.2.0; extra == "dev"
Requires-Dist: pytest<9.0.0,>=8.1.1; extra == "dev"
Requires-Dist: pytest-asyncio<1.0.0,>=0.23.6; extra == "dev"
Requires-Dist: pytest-cov<6.0.0,>=5.0.0; extra == "dev"
Requires-Dist: ruff<1.0.0,>=0.6.7; extra == "dev"
Requires-Dist: ipython<10.0.0,>=9.4.0; extra == "dev"
Provides-Extra: flair
Requires-Dist: flair<0.16.0,>=0.15.0; extra == "flair"
Provides-Extra: transformers
Requires-Dist: transformers<5.0.0,>=4.53.3; extra == "transformers"
Requires-Dist: huggingface_hub; extra == "transformers"
Requires-Dist: spacy_huggingface_pipelines==0.0.4; extra == "transformers"
Provides-Extra: optimum-onnx
Requires-Dist: transformers<5.0.0,>=4.53.3; extra == "optimum-onnx"
Requires-Dist: huggingface_hub; extra == "optimum-onnx"
Requires-Dist: spacy_huggingface_pipelines==0.0.4; extra == "optimum-onnx"
Requires-Dist: onnx; extra == "optimum-onnx"
Requires-Dist: optimum; extra == "optimum-onnx"
Requires-Dist: onnxruntime; extra == "optimum-onnx"
Provides-Extra: optimum-cuda
Requires-Dist: transformers<5.0.0,>=4.53.3; extra == "optimum-cuda"
Requires-Dist: huggingface_hub; extra == "optimum-cuda"
Requires-Dist: spacy_huggingface_pipelines==0.0.4; extra == "optimum-cuda"
Requires-Dist: onnx; extra == "optimum-cuda"
Requires-Dist: optimum; extra == "optimum-cuda"
Requires-Dist: onnxruntime-gpu; sys_platform != "darwin" and extra == "optimum-cuda"
Provides-Extra: torch
Requires-Dist: torch<3.0.0,>2.0.0; extra == "torch"
